backupdb/__init__.py
backupdb/cli.py
backupdb/pgdump.py
backupdb/storage.py
backupdb-0.0.5.dist-info/LICENSE
backupdb-0.0.5.dist-info/METADATA
backupdb-0.0.5.dist-info/WHEEL
backupdb-0.0.5.dist-info/entry_points.txt
backupdb-0.0.5.dist-info/top_level.txt
backupdb-0.0.5.dist-info/RECORD
