Metadata-Version: 2.1
Name: backupdb
Version: 0.0.5
Summary: A simple CLI utility for backing up PostgreSQL databases.
Home-page: https://github.com/sharhan-alhassan/backupdb
Author: Sharhan Alhassan
Author-email: sharhanalhassan@gmail.com
License: UNKNOWN
Platform: UNKNOWN
Classifier: Programming Language :: Python :: 3.9
Classifier: License :: OSI Approved :: MIT License
Requires-Python: >=3.9
Requires-Dist: boto3 (==1.19.7)
Requires-Dist: botocore (==1.22.7)
Requires-Dist: jmespath (==0.10.0)
Requires-Dist: python-dateutil (==2.8.2)
Requires-Dist: s3transfer (==0.5.0)
Requires-Dist: six (==1.16.0)
Requires-Dist: urllib3 (==1.26.7)
